aptible_client/__init__.py
aptible_client/_version.py
aptible_client/api_client.py
aptible_client/configuration.py
aptible_client/exceptions.py
aptible_client/model_utils.py
aptible_client/py.typed
aptible_client/rest.py
aptible_client/api/__init__.py
aptible_client/api/actions_api.py
aptible_client/api/assets_api.py
aptible_client/api/connections_api.py
aptible_client/api/default_api.py
aptible_client/api/environments_api.py
aptible_client/api/operations_api.py
aptible_client/api/organizations_api.py
aptible_client/api/utilities_api.py
aptible_client/api/worker_api.py
aptible_client/apis/__init__.py
aptible_client/helpers/__init__.py
aptible_client/helpers/constants.py
aptible_client/helpers/exceptions.py
aptible_client/helpers/logger_utils.py
aptible_client/helpers/misc.py
aptible_client/helpers/waiters.py
aptible_client/model/__init__.py
aptible_client/model/action_output.py
aptible_client/model/action_request.py
aptible_client/model/action_response.py
aptible_client/model/asset_action.py
aptible_client/model/asset_bundle.py
aptible_client/model/asset_input.py
aptible_client/model/asset_output.py
aptible_client/model/asset_parameters_output.py
aptible_client/model/asset_status.py
aptible_client/model/asset_terraform_output.py
aptible_client/model/connection_input.py
aptible_client/model/connection_output.py
aptible_client/model/connection_status.py
aptible_client/model/data.py
aptible_client/model/environment_input.py
aptible_client/model/environment_output.py
aptible_client/model/health_check_from_worker.py
aptible_client/model/http_validation_error.py
aptible_client/model/location_inner.py
aptible_client/model/operation_action_update.py
aptible_client/model/operation_asset_update.py
aptible_client/model/operation_failure.py
aptible_client/model/operation_output.py
aptible_client/model/operation_status.py
aptible_client/model/operation_terraform_run_update.py
aptible_client/model/operation_type.py
aptible_client/model/operation_update.py
aptible_client-1.3.1.dist-info/METADATA
aptible_client-1.3.1.dist-info/WHEEL
aptible_client-1.3.1.dist-info/top_level.txt
aptible_client-1.3.1.dist-info/RECORD
