Metadata-Version: 2.1
Name: aptible-client
Version: 1.3.1
Summary: Aptible Client API
Home-page: https://github.com/aptible/cloud-api-clients
Author: Aptible
Author-email: contact@aptible.com
License: MIT
Keywords: OpenAPI,OpenAPI-Generator,Cloud API
Requires-Python: >=3.6
Requires-Dist: urllib3 (>=1.25.3)
Requires-Dist: python-dateutil
